speeedy/__init__.py
speeedy/speeedy.py
speeedy-0.0.3.dist-info/LICENSE.txt
speeedy-0.0.3.dist-info/METADATA
speeedy-0.0.3.dist-info/WHEEL
speeedy-0.0.3.dist-info/top_level.txt
speeedy-0.0.3.dist-info/RECORD
