Metadata-Version: 2.2
Name: Speeedy
Version: 0.0.3
Summary: Speeedy
Author-email: Denis Minka <minka.denis@gmail.com>
License-File: LICENSE.txt
